README.md
setup.cfg
setup.py
lollygag/__init__.py
lollygag/__main__.py
lollygag/app.py
lollygag/data/__init__.py
lollygag/data/config.py
lollygag/data/models.py
lollygag/ui/__init__.py
lollygag/ui/mainForm.py
lollygag/ui/taskEditForm.py
lollygag/ui/tasksBox.py
lollygag/ui/viewEditForm.py
lollygag/ui/viewsBox.py
lollygag/vendor/__init__.py
lollygag/vendor/npyscreen/__init__.py
lollygag/vendor/npyscreen/apNPSApplication.py
lollygag/vendor/npyscreen/apNPSApplicationAdvanced.py
lollygag/vendor/npyscreen/apNPSApplicationEvents.py
lollygag/vendor/npyscreen/apNPSApplicationManaged.py
lollygag/vendor/npyscreen/apOptions.py
lollygag/vendor/npyscreen/eveventhandler.py
lollygag/vendor/npyscreen/fmActionForm.py
lollygag/vendor/npyscreen/fmActionFormV2.py
lollygag/vendor/npyscreen/fmFileSelector.py
lollygag/vendor/npyscreen/fmForm.py
lollygag/vendor/npyscreen/fmFormMultiPage.py
lollygag/vendor/npyscreen/fmFormMutt.py
lollygag/vendor/npyscreen/fmFormMuttActive.py
lollygag/vendor/npyscreen/fmFormWithMenus.py
lollygag/vendor/npyscreen/fmPopup.py
lollygag/vendor/npyscreen/fm_form_edit_loop.py
lollygag/vendor/npyscreen/globals.py
lollygag/vendor/npyscreen/muMenu.py
lollygag/vendor/npyscreen/muNewMenu.py
lollygag/vendor/npyscreen/npysGlobalOptions.py
lollygag/vendor/npyscreen/npysNPSFilteredData.py
lollygag/vendor/npyscreen/npysThemeManagers.py
lollygag/vendor/npyscreen/npysThemes.py
lollygag/vendor/npyscreen/npysTree.py
lollygag/vendor/npyscreen/npyspmfuncs.py
lollygag/vendor/npyscreen/npyssafewrapper.py
lollygag/vendor/npyscreen/proto_fm_screen_area.py
lollygag/vendor/npyscreen/stdfmemail.py
lollygag/vendor/npyscreen/utilNotify.py
lollygag/vendor/npyscreen/util_viewhelp.py
lollygag/vendor/npyscreen/wgFormControlCheckbox.py
lollygag/vendor/npyscreen/wgNMenuDisplay.py
lollygag/vendor/npyscreen/wgannotatetextbox.py
lollygag/vendor/npyscreen/wgautocomplete.py
lollygag/vendor/npyscreen/wgboxwidget.py
lollygag/vendor/npyscreen/wgbutton.py
lollygag/vendor/npyscreen/wgcheckbox.py
lollygag_cli.egg-info/PKG-INFO
lollygag_cli.egg-info/SOURCES.txt
lollygag_cli.egg-info/dependency_links.txt
lollygag_cli.egg-info/entry_points.txt
lollygag_cli.egg-info/requires.txt
lollygag_cli.egg-info/top_level.txt