Metadata-Version: 2.1
Name: lollygag-cli
Version: 0.0.1
Summary: a flexible task manager
Home-page: https://github.com/pvwoods/lollygag
Author: Philip Woods
License: MIT
Keywords: task manager cli tasks
Platform: UNKNOWN
Classifier: Programming Language :: Python :: 3
Classifier: Programming Language :: Python :: 3.5
Classifier: Programming Language :: Python :: 3.6
Classifier: Programming Language :: Python :: 3.7
Classifier: License :: OSI Approved :: MIT License
Requires-Python: >=3.5
